pymailauth/__init__.py
pymailauth/consts.py
pymailauth/service.py
pymailauth-1.2.1.dist-info/METADATA
pymailauth-1.2.1.dist-info/WHEEL
pymailauth-1.2.1.dist-info/top_level.txt
pymailauth-1.2.1.dist-info/RECORD
