Metadata-Version: 2.1
Name: pymailauth
Version: 1.2.1
Summary: Python mail client for GMail
Home-page: https://github.com/itsankitkp/pymailauth
Author: Ankit Kumar Pandey
Author-email: itsankitkp@gmail.com
Keywords: mail
Classifier: Programming Language :: Python :: 3
Requires-Dist: google-auth (==2.17.3)
Requires-Dist: google-auth-oauthlib (==1.0.0)
Requires-Dist: google-auth-httplib2 (==0.1.0)
Requires-Dist: google-api-python-client (==2.86.0)
